saltbox/__init__.py
saltbox/exceptions.py
saltbox/saltbox.py
saltbox/utils.py
saltbox-0.1.3.dist-info/LICENSE
saltbox-0.1.3.dist-info/METADATA
saltbox-0.1.3.dist-info/WHEEL
saltbox-0.1.3.dist-info/top_level.txt
saltbox-0.1.3.dist-info/RECORD
