Metadata-Version: 2.1
Name: saltbox
Version: 0.1.3
Summary: Interface with your Salt Fiber Box router in python.
Home-page: https://github.com/bjornorri/pysaltbox
Author: Björn Orri Saemundsson
Author-email: bjornorri@gmail.com
License: UNKNOWN
Platform: UNKNOWN
Classifier: Programming Language :: Python :: 3
Classifier: License :: OSI Approved :: MIT License
Classifier: Operating System :: OS Independent
Requires-Python: >=3.6
Requires-Dist: beautifulsoup4 (==4.8.2)
Requires-Dist: certifi (==2019.11.28)
Requires-Dist: chardet (==3.0.4)
Requires-Dist: idna (==2.8)
Requires-Dist: requests (==2.22.0)
Requires-Dist: soupsieve (==1.9.5)
Requires-Dist: urllib3 (==1.25.7)
